{"ongoing_trials": {}, "hyperparameters": {"space": [{"class_name": "Choice", "config": {"name": "activation", "default": "relu", "conditions": [], "values": ["relu", "tanh", "sigmoid", "elu", "selu", "gelu"], "ordered": false}}, {"class_name": "Int", "config": {"name": "num_layers", "default": null, "conditions": [], "min_value": 6, "max_value": 10, "step": 1, "sampling": "linear"}}, {"class_name": "Choice", "config": {"name": "optimizer", "default": "adam", "conditions": [], "values": ["adam", "sgd", "rmsprop", "adamax", "nadam"], "ordered": false}}, {"class_name": "Choice", "config": {"name": "batch_size", "default": 16, "conditions": [], "values": [16, 32, 64], "ordered": true}}], "values": {"activation": "relu", "num_layers": 6, "optimizer": "adam", "batch_size": 16}}, "start_order": ["0", "1", "2", "3", "4", "5", "6", "7"], "end_order": ["0", "1", "2", "3", "4", "5", "6", "7"], "run_times": {"0": 1, "1": 1, "2": 1, "3": 1, "4": 1, "5": 1, "6": 1, "7": 1}, "retry_queue": [], "seed": 8818, "seed_state": 8850, "tried_so_far": ["b9c1f565c852465f2b742d5919c8e3d3", "a3172e1c8fbf2244335d342f050a318c", "7b3bdbe89368c36a96e58b8caf95989d", "bd3b6c1c7cae33518b9bac2998e6ded9", "3b5bd55dc44b862e403dff748ec2c5fc", "c657fd88b2caadc0b6c39cd4a371fb48", "5e0740aa77872a171313de1b16908f07", "555fcf122002bac2cbedcbe7e79e7eb3"], "id_to_hash": {"0": "b9c1f565c852465f2b742d5919c8e3d3", "1": "7b3bdbe89368c36a96e58b8caf95989d", "2": "a3172e1c8fbf2244335d342f050a318c", "3": "c657fd88b2caadc0b6c39cd4a371fb48", "4": "bd3b6c1c7cae33518b9bac2998e6ded9", "5": "555fcf122002bac2cbedcbe7e79e7eb3", "6": "3b5bd55dc44b862e403dff748ec2c5fc", "7": "5e0740aa77872a171313de1b16908f07"}, "display": {"search_start": "2025-03-14T23:07:27.028067", "trial_start": {"0": "2025-03-14T23:07:27.028067", "1": "2025-03-14T23:07:40.687398", "2": "2025-03-14T23:08:04.806752", "3": "2025-03-14T23:08:23.315487", "4": "2025-03-14T23:08:35.683824", "5": "2025-03-14T23:08:51.331011", "6": "2025-03-14T23:09:05.958756", "7": "2025-03-14T23:09:26.514510"}, "trial_number": {"0": 1, "1": 2, "2": 3, "3": 4, "4": 5, "5": 6, "6": 7, "7": 8}}, "num_initial_points": null, "alpha": 0.0001, "beta": 2.6}